bert_schemas/__init__.py
bert_schemas/job.py
bert_schemas/message.py
bert_schemas/projected.py
bert_schemas/qpu.py
bert_schemas/qpu_access.py
bert_schemas/questionnaire.py
bert_schemas/report.py
bert_schemas/testing/__init__.py
bert_schemas/testing/factories/__init__.py
bert_schemas/testing/factories/helpers.py
bert_schemas/testing/factories/job.py
bert_schemas/testing/fixtures/__init__.py
bert_schemas/testing/fixtures/job.py
bert_schemas/tests/__init__.py
bert_schemas/tests/test_job_schemas.py
bert_schemas/tests/test_projected.py
bert_schemas/tests/test_timing.py
bert_schemas/timing.py
bert_schemas/user.py
bert_schemas-4.6.11.dist-info/LICENSE
bert_schemas-4.6.11.dist-info/METADATA
bert_schemas-4.6.11.dist-info/WHEEL
bert_schemas-4.6.11.dist-info/RECORD
