Metadata-Version: 2.1
Name: bert-schemas
Version: 4.6.11
Summary: Bert service schemas
License: Apache-2.0
Author: Larry Buza
Author-email: lawrence.buza@infleqtion.com
Requires-Python: >=3.10,<4.0
Classifier: License :: OSI Approved :: Apache Software License
Classifier: Operating System :: OS Independent
Classifier: Programming Language :: Python :: 3
Classifier: Programming Language :: Python :: 3.10
Classifier: Programming Language :: Python :: 3.11
Classifier: Programming Language :: Python :: 3.12
Requires-Dist: faker (>=33.1.0,<34.0.0)
Requires-Dist: matplotlib (>=3.6.2,<3.7.0)
Requires-Dist: polyfactory (>=2.8.0,<3.0.0)
Requires-Dist: pydantic[email] (>=2.3.0,<3.0.0)
Requires-Dist: pytest (>=8.2.0,<9.0.0)
Requires-Dist: scipy (>=1.10.0,<2.0.0)
